cenv_tool-3.0.1.dist-info/dependency_links.txt
cenv_tool-3.0.1.dist-info/entry_points.txt
cenv_tool-3.0.1.dist-info/METADATA
cenv_tool-3.0.1.dist-info/top_level.txt
cenv_tool-3.0.1.dist-info/WHEEL
cenv_tool/project.py
cenv_tool/utils.py
cenv_tool/init_cenv.py
cenv_tool/schemata.py
cenv_tool/__init__.py
cenv_tool/rules.py
cenv_tool/cenv.sh
cenv_tool/cenv.yml
cenv_tool-3.0.1.dist-info/LICENSE.txt
cenv_tool-3.0.1.dist-info/RECORD