Metadata-Version: 2.1
Name: cenv-tool
Version: 3.0.1
Summary: conda environment creation and update from meta.yaml
Home-Page: https://www.cenv.ouroboros.info
Project-URL: Repository, https://github.com/skallfass/cenv_tool
Author: Simon Kallfass
Author-email: skallfass@ouroboros.info
License: MIT
Requires-Python: >=3.7
Keywords: conda,environment,dependencies
Classifier: Operating System :: Unix
Classifier: License :: OSI Approved :: MIT License
Classifier: Programming Language :: Python :: 3.7
Requires-Dist: attrs>=19
Requires-Dist: coverage>=4; extra == "tests" or extra == "dev"
Requires-Dist: coverage-badge>=1; extra == "tests" or extra == "dev"
Requires-Dist: ipython>=7; extra == "dev"
Requires-Dist: jinja2>=2
Requires-Dist: marshmallow<3,>=2.19
Requires-Dist: pylint>=2.4; extra == "dev"
Requires-Dist: pytest>=5; extra == "tests" or extra == "dev"
Requires-Dist: pytest-cov>=2; extra == "tests" or extra == "dev"
Requires-Dist: pytest-datafiles>=2; extra == "tests" or extra == "dev"
Requires-Dist: pyyaml==5.*,>=5.0.0
Requires-Dist: six>=1.12
Requires-Dist: sphinx>=2; extra == "docs" or extra == "dev"
Requires-Dist: sphinx-autodoc-typehints>=1.8.0; extra == "docs" or extra == "dev"
Requires-Dist: sphinx-rtd-theme>=0; extra == "dev"
Requires-Dist: yapf>=0; extra == "dev"
Provides-Extra: dev
Provides-Extra: docs
Provides-Extra: tests
